{
  "matches": [
    {
      "date": "2026-06-13",
      "match": "澳大利亚 vs 土耳其",
      "score": "2:0",
      "goals": 2,
      "had": "主胜",
      "stage": "D组"
    },
    {
      "date": "2026-06-13",
      "match": "卡塔尔 vs 瑞士",
      "score": "1:1",
      "goals": 2,
      "had": "平",
      "stage": "B组"
    },
    {
      "date": "2026-06-19",
      "match": "美国 vs 澳大利亚",
      "score": "2:0",
      "goals": 2,
      "had": "主胜",
      "stage": "D组"
    },
    {
      "date": "2026-06-20",
      "match": "德国 vs 科特迪瓦",
      "score": "2:1",
      "goals": 3,
      "had": "主胜",
      "stage": "E组"
    },
    {
      "date": "2026-06-20",
      "match": "荷兰 vs 瑞典",
      "score": "5:1",
      "goals": 6,
      "had": "主胜",
      "stage": "F组"
    },
    {
      "date": "2026-06-22",
      "match": "法国 vs 伊拉克",
      "score": "3:0",
      "goals": 3,
      "had": "主胜",
      "stage": "I组"
    },
    {
      "date": "2026-06-22",
      "match": "挪威 vs 塞内加尔",
      "score": "3:2",
      "goals": 5,
      "had": "主胜",
      "stage": "I组"
    },
    {
      "date": "2026-06-25",
      "match": "日本 vs 瑞典",
      "score": "1:1",
      "goals": 2,
      "had": "平",
      "stage": "F组"
    },
    {
      "date": "2026-06-13",
      "match": "海地 vs 苏格兰",
      "score": "0:1",
      "goals": 1,
      "had": "客胜",
      "stage": "C组"
    },
    {
      "date": "2026-06-17",
      "match": "英格兰 vs 克罗地亚",
      "score": "4:2",
      "goals": 6,
      "had": "主胜",
      "stage": "L组"
    },
    {
      "date": "2026-06-21",
      "match": "西班牙 vs 沙特",
      "score": "4:0",
      "goals": 4,
      "had": "主胜",
      "stage": "H组"
    },
    {
      "date": "2026-06-22",
      "match": "约旦 vs 阿尔及利亚",
      "score": "1:2",
      "goals": 3,
      "had": "客胜",
      "stage": "J组"
    },
    {
      "date": "2026-06-23",
      "match": "葡萄牙 vs 乌兹别克",
      "score": "5:0",
      "goals": 5,
      "had": "主胜",
      "stage": "K组"
    },
    {
      "date": "2026-06-23",
      "match": "巴拿马 vs 克罗地亚",
      "score": "0:1",
      "goals": 1,
      "had": "客胜",
      "stage": "L组"
    },
    {
      "date": "2026-06-24",
      "match": "捷克 vs 墨西哥",
      "score": "0:3",
      "goals": 3,
      "had": "客胜",
      "stage": "A组"
    },
    {
      "date": "2026-06-25",
      "match": "突尼斯 vs 荷兰",
      "score": "1:3",
      "goals": 4,
      "had": "客胜",
      "stage": "F组"
    },
    {
      "date": "2026-06-11",
      "match": "韩国 vs 捷克",
      "score": "2:1",
      "goals": 3,
      "had": "主胜",
      "stage": "A组"
    },
    {
      "date": "2026-06-12",
      "match": "美国 vs 巴拉圭",
      "score": "4:1",
      "goals": 5,
      "had": "主胜",
      "stage": "D组"
    },
    {
      "date": "2026-06-16",
      "match": "法国 vs 塞内加尔",
      "score": "3:1",
      "goals": 4,
      "had": "主胜",
      "stage": "I组"
    },
    {
      "date": "2026-06-16",
      "match": "伊拉克 vs 挪威",
      "score": "1:4",
      "goals": 5,
      "had": "客胜",
      "stage": "I组"
    },
    {
      "date": "2026-06-17",
      "match": "葡萄牙 vs 刚果金",
      "score": "1:1",
      "goals": 2,
      "had": "平",
      "stage": "K组"
    },
    {
      "date": "2026-06-21",
      "match": "比利时 vs 伊朗",
      "score": "0:0",
      "goals": 0,
      "had": "平",
      "stage": "G组"
    },
    {
      "date": "2026-06-24",
      "match": "摩洛哥 vs 海地",
      "score": "4:2",
      "goals": 6,
      "had": "主胜",
      "stage": "C组"
    },
    {
      "date": "2026-06-24",
      "match": "南非 vs 韩国",
      "score": "1:0",
      "goals": 1,
      "had": "主胜",
      "stage": "A组"
    },
    {
      "date": "2026-06-14",
      "match": "科特迪瓦 vs 厄瓜多尔",
      "score": "1:0",
      "goals": 1,
      "had": "主胜",
      "stage": "E组"
    },
    {
      "date": "2026-06-14",
      "match": "德国 vs 库拉索",
      "score": "7:1",
      "goals": 8,
      "had": "主胜",
      "stage": "E组"
    },
    {
      "date": "2026-06-14",
      "match": "瑞典 vs 突尼斯",
      "score": "5:1",
      "goals": 6,
      "had": "主胜",
      "stage": "F组"
    },
    {
      "date": "2026-06-18",
      "match": "墨西哥 vs 韩国",
      "score": "1:0",
      "goals": 1,
      "had": "主胜",
      "stage": "A组"
    },
    {
      "date": "2026-06-18",
      "match": "加拿大 vs 卡塔尔",
      "score": "6:0",
      "goals": 6,
      "had": "主胜",
      "stage": "B组"
    },
    {
      "date": "2026-06-19",
      "match": "苏格兰 vs 摩洛哥",
      "score": "0:1",
      "goals": 1,
      "had": "客胜",
      "stage": "C组"
    },
    {
      "date": "2026-06-19",
      "match": "土耳其 vs 巴拉圭",
      "score": "0:1",
      "goals": 1,
      "had": "客胜",
      "stage": "D组"
    },
    {
      "date": "2026-06-22",
      "match": "阿根廷 vs 奥地利",
      "score": "2:0",
      "goals": 2,
      "had": "主胜",
      "stage": "J组"
    },
    {
      "date": "2026-06-24",
      "match": "苏格兰 vs 巴西",
      "score": "0:3",
      "goals": 3,
      "had": "客胜",
      "stage": "C组"
    },
    {
      "date": "2026-06-24",
      "match": "波黑 vs 卡塔尔",
      "score": "3:1",
      "goals": 4,
      "had": "主胜",
      "stage": "B组"
    },
    {
      "date": "2026-06-25",
      "match": "土耳其 vs 美国",
      "score": "3:2",
      "goals": 5,
      "had": "主胜",
      "stage": "D组"
    },
    {
      "date": "2026-06-11",
      "match": "墨西哥 vs 南非",
      "score": "2:0",
      "goals": 2,
      "had": "主胜",
      "stage": "A组"
    },
    {
      "date": "2026-06-13",
      "match": "巴西 vs 摩洛哥",
      "score": "1:1",
      "goals": 2,
      "had": "平",
      "stage": "C组"
    },
    {
      "date": "2026-06-14",
      "match": "荷兰 vs 日本",
      "score": "2:2",
      "goals": 4,
      "had": "平",
      "stage": "F组"
    },
    {
      "date": "2026-06-18",
      "match": "瑞士 vs 波黑",
      "score": "4:1",
      "goals": 5,
      "had": "主胜",
      "stage": "B组"
    },
    {
      "date": "2026-06-19",
      "match": "巴西 vs 海地",
      "score": "3:0",
      "goals": 3,
      "had": "主胜",
      "stage": "C组"
    },
    {
      "date": "2026-06-20",
      "match": "突尼斯 vs 日本",
      "score": "0:4",
      "goals": 4,
      "had": "客胜",
      "stage": "F组"
    },
    {
      "date": "2026-06-21",
      "match": "新西兰 vs 埃及",
      "score": "1:3",
      "goals": 4,
      "had": "客胜",
      "stage": "G组"
    },
    {
      "date": "2026-06-21",
      "match": "乌拉圭 vs 佛得角",
      "score": "2:2",
      "goals": 4,
      "had": "平",
      "stage": "H组"
    },
    {
      "date": "2026-06-23",
      "match": "哥伦比亚 vs 刚果金",
      "score": "1:0",
      "goals": 1,
      "had": "主胜",
      "stage": "K组"
    },
    {
      "date": "2026-06-15",
      "match": "西班牙 vs 佛得角",
      "score": "0:0",
      "goals": 0,
      "had": "平",
      "stage": "H组"
    },
    {
      "date": "2026-06-15",
      "match": "沙特 vs 乌拉圭",
      "score": "1:1",
      "goals": 2,
      "had": "平",
      "stage": "H组"
    },
    {
      "date": "2026-06-16",
      "match": "奥地利 vs 约旦",
      "score": "3:1",
      "goals": 4,
      "had": "主胜",
      "stage": "J组"
    },
    {
      "date": "2026-06-17",
      "match": "乌兹别克 vs 哥伦比亚",
      "score": "1:3",
      "goals": 4,
      "had": "客胜",
      "stage": "K组"
    },
    {
      "date": "2026-06-12",
      "match": "加拿大 vs 波黑",
      "score": "1:1",
      "goals": 2,
      "had": "平",
      "stage": "B组"
    },
    {
      "date": "2026-06-15",
      "match": "伊朗 vs 新西兰",
      "score": "2:2",
      "goals": 4,
      "had": "平",
      "stage": "G组"
    },
    {
      "date": "2026-06-16",
      "match": "阿根廷 vs 阿尔及利亚",
      "score": "3:0",
      "goals": 3,
      "had": "主胜",
      "stage": "J组"
    },
    {
      "date": "2026-06-17",
      "match": "加纳 vs 巴拿马",
      "score": "1:0",
      "goals": 1,
      "had": "主胜",
      "stage": "L组"
    },
    {
      "date": "2026-06-18",
      "match": "捷克 vs 南非",
      "score": "1:1",
      "goals": 2,
      "had": "平",
      "stage": "A组"
    },
    {
      "date": "2026-06-23",
      "match": "英格兰 vs 加纳",
      "score": "0:0",
      "goals": 0,
      "had": "平",
      "stage": "L组"
    },
    {
      "date": "2026-06-25",
      "match": "库拉索 vs 科特迪瓦",
      "score": "0:2",
      "goals": 2,
      "had": "客胜",
      "stage": "E组"
    },
    {
      "date": "2026-06-25",
      "match": "厄瓜多尔 vs 德国",
      "score": "2:1",
      "goals": 3,
      "had": "主胜",
      "stage": "E组"
    },
    {
      "date": "2026-06-15",
      "match": "比利时 vs 埃及",
      "score": "1:1",
      "goals": 2,
      "had": "平",
      "stage": "G组"
    },
    {
      "date": "2026-06-20",
      "match": "厄瓜多尔 vs 库拉索",
      "score": "0:0",
      "goals": 0,
      "had": "平",
      "stage": "E组"
    },
    {
      "date": "2026-06-24",
      "match": "瑞士 vs 加拿大",
      "score": "2:1",
      "goals": 3,
      "had": "主胜",
      "stage": "B组"
    },
    {
      "date": "2026-06-25",
      "match": "巴拉圭 vs 澳大利亚",
      "score": "0:0",
      "goals": 0,
      "had": "平",
      "stage": "D组"
    }
  ],
  "teams": {},
  "patterns": {
    "super_draw": 16,
    "super_win": 19,
    "total_cold": 29,
    "updated": "2026-06-26"
  },
  "odds_snapshots": {
    "2040182": {
      "had_h": 1.13,
      "had_d": 5.86,
      "had_a": 13.5,
      "hhad_h": 2.47,
      "hhad_d": 3.92,
      "hhad_a": 2.13,
      "hhad_line": "-2",
      "time": "06-17 22:17"
    },
    "2040183": {
      "had_h": 1.54,
      "had_d": 3.45,
      "had_a": 5.25,
      "hhad_h": 2.98,
      "hhad_d": 3.0,
      "hhad_a": 2.17,
      "hhad_line": "-1",
      "time": "06-17 22:17"
    },
    "2040184": {
      "had_h": 2.04,
      "had_d": 3.03,
      "had_a": 3.23,
      "hhad_h": 4.2,
      "hhad_d": 3.7,
      "hhad_a": 1.61,
      "hhad_line": "-1",
      "time": "06-17 22:17"
    },
    "2040185": {
      "had_h": 9.65,
      "had_d": 4.85,
      "had_a": 1.22,
      "hhad_h": 3.37,
      "hhad_d": 3.58,
      "hhad_a": 1.81,
      "hhad_line": "+1",
      "time": "06-17 22:17"
    },
    "2040228": {
      "had_h": 2.5,
      "had_d": 2.9,
      "had_a": 2.6,
      "hhad_h": 5.35,
      "hhad_d": 4.5,
      "hhad_a": 1.39,
      "hhad_line": "-1",
      "time": "06-17 22:17"
    },
    "2040229": {
      "had_h": 1.46,
      "had_d": 4.1,
      "had_a": 5.0,
      "hhad_h": 2.4,
      "hhad_d": 3.5,
      "hhad_a": 2.34,
      "hhad_line": "-1",
      "time": "06-17 22:17"
    },
    "2040230": {
      "had_h": 5.05,
      "had_d": 3.5,
      "had_a": 1.55,
      "hhad_h": 2.15,
      "hhad_d": 3.12,
      "hhad_a": 2.91,
      "hhad_line": "+1",
      "time": "06-17 22:17"
    },
    "2040231": {
      "had_h": 2.31,
      "had_d": 3.0,
      "had_a": 2.76,
      "hhad_h": 5.05,
      "hhad_d": 4.0,
      "hhad_a": 1.47,
      "hhad_line": "-1",
      "time": "06-17 22:17"
    },
    "2040232": {
      "had_h": 2.25,
      "had_d": 3.21,
      "had_a": 2.68,
      "hhad_h": 4.7,
      "hhad_d": 4.0,
      "hhad_a": 1.5,
      "hhad_line": "-1",
      "time": "06-17 22:17"
    },
    "2040235": {
      "had_h": 1.59,
      "had_d": 3.55,
      "had_a": 4.58,
      "hhad_h": 2.95,
      "hhad_d": 3.3,
      "hhad_a": 2.05,
      "hhad_line": "-1",
      "time": "06-18 21:02"
    },
    "2040236": {
      "had_h": 1.38,
      "had_d": 3.95,
      "had_a": 6.6,
      "hhad_h": 2.4,
      "hhad_d": 3.15,
      "hhad_a": 2.53,
      "hhad_line": "-1",
      "time": "06-18 21:02"
    },
    "2040237": {
      "had_h": 1.17,
      "had_d": 5.45,
      "had_a": 11.0,
      "hhad_h": 1.67,
      "hhad_d": 3.65,
      "hhad_a": 3.9,
      "hhad_line": "-1",
      "time": "06-18 21:02"
    },
    "2040238": {
      "had_h": 1.91,
      "had_d": 2.86,
      "had_a": 3.9,
      "hhad_h": 4.16,
      "hhad_d": 3.32,
      "hhad_a": 1.7,
      "hhad_line": "-1",
      "time": "06-18 21:02"
    },
    "2040233": {
      "had_h": 1.26,
      "had_d": 4.65,
      "had_a": 8.25,
      "hhad_h": 1.96,
      "hhad_d": 3.4,
      "hhad_a": 3.08,
      "hhad_line": "-1",
      "time": "06-17 22:17"
    },
    "2040239": {
      "had_h": 1.45,
      "had_d": 3.83,
      "had_a": 5.6,
      "hhad_h": 2.51,
      "hhad_d": 3.25,
      "hhad_a": 2.36,
      "hhad_line": "-1",
      "time": "06-19 13:40"
    },
    "2040240": {
      "had_h": 5.35,
      "had_d": 3.42,
      "had_a": 1.54,
      "hhad_h": 2.14,
      "hhad_d": 3.18,
      "hhad_a": 2.88,
      "hhad_line": "+1",
      "time": "06-19 13:40"
    },
    "2040241": {
      "had_h": null,
      "had_d": null,
      "had_a": null,
      "hhad_h": 1.69,
      "hhad_d": 4.2,
      "hhad_a": 3.35,
      "hhad_line": "-2",
      "time": "06-19 13:40"
    },
    "2040242": {
      "had_h": 1.82,
      "had_d": 3.22,
      "had_a": 3.72,
      "hhad_h": 3.72,
      "hhad_d": 3.35,
      "hhad_a": 1.78,
      "hhad_line": "-1",
      "time": "06-19 13:40"
    },
    "2040243": {
      "had_h": 1.59,
      "had_d": 3.58,
      "had_a": 4.52,
      "hhad_h": 2.86,
      "hhad_d": 3.45,
      "hhad_a": 2.04,
      "hhad_line": "-1",
      "time": "06-19 13:40"
    },
    "2040244": {
      "had_h": 1.4,
      "had_d": 4.15,
      "had_a": 5.75,
      "hhad_h": 2.27,
      "hhad_d": 3.55,
      "hhad_a": 2.46,
      "hhad_line": "-1",
      "time": "06-19 13:40"
    },
    "2040245": {
      "had_h": null,
      "had_d": null,
      "had_a": null,
      "hhad_h": 1.95,
      "hhad_d": 3.95,
      "hhad_a": 2.75,
      "hhad_line": "-2",
      "time": "06-19 13:40"
    },
    "2040246": {
      "had_h": 6.0,
      "had_d": 3.8,
      "had_a": 1.43,
      "hhad_h": 2.38,
      "hhad_d": 3.25,
      "hhad_a": 2.49,
      "hhad_line": "+1",
      "time": "06-19 13:40"
    },
    "2040247": {
      "had_h": null,
      "had_d": null,
      "had_a": null,
      "hhad_h": 1.59,
      "hhad_d": 4.55,
      "hhad_a": 3.56,
      "hhad_line": "-2",
      "time": "06-21 19:13"
    },
    "2040248": {
      "had_h": 1.26,
      "had_d": 4.76,
      "had_a": 7.95,
      "hhad_h": 1.89,
      "hhad_d": 3.72,
      "hhad_a": 3.02,
      "hhad_line": "-1",
      "time": "06-21 19:13"
    },
    "2040249": {
      "had_h": 1.29,
      "had_d": 4.15,
      "had_a": 8.8,
      "hhad_h": 2.08,
      "hhad_d": 3.3,
      "hhad_a": 2.89,
      "hhad_line": "-1",
      "time": "06-21 19:13"
    },
    "2040250": {
      "had_h": 6.0,
      "had_d": 3.87,
      "had_a": 1.42,
      "hhad_h": 2.46,
      "hhad_d": 3.3,
      "hhad_a": 2.38,
      "hhad_line": "+1",
      "time": "06-21 19:13"
    },
    "2040251": {
      "had_h": 1.4,
      "had_d": 3.98,
      "had_a": 6.1,
      "hhad_h": 2.28,
      "hhad_d": 3.48,
      "hhad_a": 2.48,
      "hhad_line": "-1",
      "time": "06-21 19:13"
    },
    "2040252": {
      "had_h": null,
      "had_d": null,
      "had_a": null,
      "hhad_h": 2.61,
      "hhad_d": 4.5,
      "hhad_a": 1.91,
      "hhad_line": "-3",
      "time": "06-21 19:13"
    },
    "2040253": {
      "had_h": 1.95,
      "had_d": 3.3,
      "had_a": 3.2,
      "hhad_h": 3.88,
      "hhad_d": 3.82,
      "hhad_a": 1.64,
      "hhad_line": "-1",
      "time": "06-21 19:13"
    },
    "2040254": {
      "had_h": 5.82,
      "had_d": 3.8,
      "had_a": 1.44,
      "hhad_h": 2.4,
      "hhad_d": 3.35,
      "hhad_a": 2.42,
      "hhad_line": "+1",
      "time": "06-21 19:13"
    },
    "2040255": {
      "had_h": null,
      "had_d": null,
      "had_a": null,
      "hhad_h": 2.39,
      "hhad_d": 3.9,
      "hhad_a": 2.2,
      "hhad_line": "-2",
      "time": "06-21 19:13"
    },
    "2040256": {
      "had_h": null,
      "had_d": null,
      "had_a": null,
      "hhad_h": 2.49,
      "hhad_d": 3.9,
      "hhad_a": 2.12,
      "hhad_line": "-2",
      "time": "06-21 19:13"
    },
    "2040257": {
      "had_h": 6.0,
      "had_d": 3.95,
      "had_a": 1.41,
      "hhad_h": 2.42,
      "hhad_d": 3.4,
      "hhad_a": 2.37,
      "hhad_line": "+1",
      "time": "06-21 19:13"
    },
    "2040258": {
      "had_h": 1.36,
      "had_d": 3.85,
      "had_a": 7.5,
      "hhad_h": 2.27,
      "hhad_d": 3.3,
      "hhad_a": 2.6,
      "hhad_line": "-1",
      "time": "06-21 19:13"
    },
    "2040291": [
      {
        "had_h": 5.0,
        "had_d": 4.9,
        "had_a": 1.38,
        "hhad_h": 2.56,
        "hhad_d": 3.75,
        "hhad_a": 2.12,
        "hhad_line": "+1",
        "time": "06-25 21:40"
      }
    ],
    "2040292": [
      {
        "had_h": null,
        "had_d": null,
        "had_a": null,
        "hhad_h": 2.66,
        "hhad_d": 3.6,
        "hhad_a": 2.1,
        "hhad_line": "+2",
        "time": "06-25 21:40"
      }
    ],
    "2040293": [
      {
        "had_h": null,
        "had_d": null,
        "had_a": null,
        "hhad_h": 3.55,
        "hhad_d": 4.2,
        "hhad_a": 1.64,
        "hhad_line": "+2",
        "time": "06-25 21:40"
      }
    ],
    "2040294": [
      {
        "had_h": 1.62,
        "had_d": 3.55,
        "had_a": 4.35,
        "hhad_h": 2.95,
        "hhad_d": 3.5,
        "hhad_a": 1.98,
        "hhad_line": "-1",
        "time": "06-25 21:40"
      }
    ],
    "2040295": [
      {
        "had_h": 2.57,
        "had_d": 2.2,
        "had_a": 3.5,
        "hhad_h": 6.2,
        "hhad_d": 4.1,
        "hhad_a": 1.38,
        "hhad_line": "-1",
        "time": "06-26 09:20"
      }
    ],
    "2040296": [
      {
        "had_h": 3.75,
        "had_d": 3.9,
        "had_a": 1.65,
        "hhad_h": 1.94,
        "hhad_d": 3.93,
        "hhad_a": 2.78,
        "hhad_line": "+1",
        "time": "06-26 09:20"
      }
    ],
    "2040297": [
      {
        "had_h": 4.48,
        "had_d": 4.33,
        "had_a": 1.48,
        "hhad_h": 2.3,
        "hhad_d": 3.4,
        "hhad_a": 2.5,
        "hhad_line": "+1",
        "time": "06-26 13:02"
      }
    ],
    "2040298": [
      {
        "had_h": null,
        "had_d": null,
        "had_a": null,
        "hhad_h": 2.47,
        "hhad_d": 3.8,
        "hhad_a": 2.17,
        "hhad_line": "-2",
        "time": "06-26 13:02"
      }
    ],
    "2040299": [
      {
        "had_h": 2.4,
        "had_d": 3.05,
        "had_a": 2.6,
        "hhad_h": 5.55,
        "hhad_d": 4.0,
        "hhad_a": 1.43,
        "hhad_line": "-1",
        "time": "06-26 13:02"
      }
    ],
    "2040300": [
      {
        "had_h": 7.0,
        "had_d": 3.9,
        "had_a": 1.37,
        "hhad_h": 2.57,
        "hhad_d": 3.42,
        "hhad_a": 2.23,
        "hhad_line": "+1",
        "time": "06-26 13:02"
      }
    ],
    "2040301": [
      {
        "had_h": 2.26,
        "had_d": 2.5,
        "had_a": 3.5,
        "hhad_h": 5.25,
        "hhad_d": 3.8,
        "hhad_a": 1.48,
        "hhad_line": "-1",
        "time": "06-26 13:02"
      }
    ],
    "2040302": [
      {
        "had_h": null,
        "had_d": null,
        "had_a": null,
        "hhad_h": 2.58,
        "hhad_d": 3.95,
        "hhad_a": 2.05,
        "hhad_line": "+2",
        "time": "06-26 13:02"
      }
    ],
    "2040303": [
      {
        "had_h": 1.57,
        "had_d": 3.08,
        "had_a": 5.95,
        "hhad_h": 2.82,
        "hhad_d": 3.35,
        "hhad_a": 2.1,
        "hhad_line": "-1",
        "time": "06-26 13:02"
      }
    ],
    "2040304": [
      {
        "had_h": null,
        "had_d": null,
        "had_a": null,
        "hhad_h": 2.48,
        "hhad_d": 3.9,
        "hhad_a": 2.13,
        "hhad_line": "+2",
        "time": "06-26 13:02"
      }
    ],
    "2040305": [
      {
        "had_h": 4.1,
        "had_d": 3.25,
        "had_a": 1.73,
        "hhad_h": 1.85,
        "hhad_d": 3.5,
        "hhad_a": 3.3,
        "hhad_line": "+1",
        "time": "06-26 13:02"
      }
    ],
    "2040306": [
      {
        "had_h": 1.71,
        "had_d": 3.75,
        "had_a": 3.6,
        "hhad_h": 3.15,
        "hhad_d": 3.5,
        "hhad_a": 1.9,
        "hhad_line": "-1",
        "time": "06-26 13:02"
      }
    ],
    "2040307": [
      {
        "had_h": 3.35,
        "had_d": 2.11,
        "had_a": 2.8,
        "hhad_h": 1.31,
        "hhad_d": 4.35,
        "hhad_a": 7.35,
        "hhad_line": "+1",
        "time": "06-26 13:02"
      }
    ],
    "2040308": [
      {
        "had_h": null,
        "had_d": null,
        "had_a": null,
        "hhad_h": 2.22,
        "hhad_d": 3.85,
        "hhad_a": 2.39,
        "hhad_line": "+2",
        "time": "06-26 13:02"
      }
    ],
    "2040327": [
      {
        "had_h": 4.7,
        "had_d": 3.18,
        "had_a": 1.66,
        "hhad_h": 1.95,
        "hhad_d": 3.3,
        "hhad_a": 3.2,
        "hhad_line": "+1",
        "time": "06-26 13:02"
      }
    ],
    "2040297": [
      {
        "had_h": 4.48,
        "had_d": 4.33,
        "had_a": 1.48,
        "hhad_h": 2.3,
        "hhad_d": 3.4,
        "hhad_a": 2.5,
        "hhad_line": "+1",
        "time": "06-26 13:08"
      }
    ],
    "2040298": [
      {
        "had_h": null,
        "had_d": null,
        "had_a": null,
        "hhad_h": 2.47,
        "hhad_d": 3.8,
        "hhad_a": 2.17,
        "hhad_line": "-2",
        "time": "06-26 13:08"
      }
    ],
    "2040299": [
      {
        "had_h": 2.4,
        "had_d": 3.05,
        "had_a": 2.6,
        "hhad_h": 5.55,
        "hhad_d": 4.0,
        "hhad_a": 1.43,
        "hhad_line": "-1",
        "time": "06-26 13:08"
      }
    ],
    "2040300": [
      {
        "had_h": 7.0,
        "had_d": 3.9,
        "had_a": 1.37,
        "hhad_h": 2.57,
        "hhad_d": 3.42,
        "hhad_a": 2.23,
        "hhad_line": "+1",
        "time": "06-26 13:08"
      }
    ],
    "2040301": [
      {
        "had_h": 2.26,
        "had_d": 2.5,
        "had_a": 3.5,
        "hhad_h": 5.25,
        "hhad_d": 3.8,
        "hhad_a": 1.48,
        "hhad_line": "-1",
        "time": "06-26 13:08"
      }
    ],
    "2040302": [
      {
        "had_h": null,
        "had_d": null,
        "had_a": null,
        "hhad_h": 2.58,
        "hhad_d": 3.95,
        "hhad_a": 2.05,
        "hhad_line": "+2",
        "time": "06-26 13:08"
      }
    ],
    "2040303": [
      {
        "had_h": 1.57,
        "had_d": 3.08,
        "had_a": 5.95,
        "hhad_h": 2.82,
        "hhad_d": 3.35,
        "hhad_a": 2.1,
        "hhad_line": "-1",
        "time": "06-26 13:08"
      }
    ],
    "2040304": [
      {
        "had_h": null,
        "had_d": null,
        "had_a": null,
        "hhad_h": 2.48,
        "hhad_d": 3.9,
        "hhad_a": 2.13,
        "hhad_line": "+2",
        "time": "06-26 13:08"
      }
    ],
    "2040305": [
      {
        "had_h": 4.1,
        "had_d": 3.25,
        "had_a": 1.73,
        "hhad_h": 1.85,
        "hhad_d": 3.5,
        "hhad_a": 3.3,
        "hhad_line": "+1",
        "time": "06-26 13:08"
      }
    ],
    "2040306": [
      {
        "had_h": 1.71,
        "had_d": 3.75,
        "had_a": 3.6,
        "hhad_h": 3.15,
        "hhad_d": 3.5,
        "hhad_a": 1.9,
        "hhad_line": "-1",
        "time": "06-26 13:08"
      }
    ],
    "2040307": [
      {
        "had_h": 3.35,
        "had_d": 2.11,
        "had_a": 2.8,
        "hhad_h": 1.31,
        "hhad_d": 4.35,
        "hhad_a": 7.35,
        "hhad_line": "+1",
        "time": "06-26 13:08"
      }
    ],
    "2040308": [
      {
        "had_h": null,
        "had_d": null,
        "had_a": null,
        "hhad_h": 2.22,
        "hhad_d": 3.85,
        "hhad_a": 2.39,
        "hhad_line": "+2",
        "time": "06-26 13:08"
      }
    ],
    "2040327": [
      {
        "had_h": 4.7,
        "had_d": 3.18,
        "had_a": 1.66,
        "hhad_h": 1.95,
        "hhad_d": 3.3,
        "hhad_a": 3.2,
        "hhad_line": "+1",
        "time": "06-26 13:08"
      }
    ]
  },
  "teams_stats": {
    "德国": {
      "xG": 2.27,
      "xGA": 0.78,
      "ppg": 3.0,
      "gf": 35,
      "ga": 7,
      "p": 10,
      "w": 10,
      "d": 0,
      "l": 0,
      "cs": 50,
      "btts": 50
    },
    "阿根廷": {
      "xG": 1.74,
      "xGA": 0.71,
      "ppg": 2.7,
      "gf": 27,
      "ga": 2,
      "p": 10,
      "w": 9,
      "d": 0,
      "l": 1,
      "cs": 80,
      "btts": 10
    },
    "奥地利": {
      "xG": 1.4,
      "xGA": 0.99,
      "ppg": 2.5,
      "gf": 26,
      "ga": 5,
      "p": 10,
      "w": 8,
      "d": 1,
      "l": 1,
      "cs": 50,
      "btts": 40
    },
    "英格兰": {
      "xG": 2.24,
      "xGA": 0.56,
      "ppg": 2.5,
      "gf": 24,
      "ga": 2,
      "p": 10,
      "w": 8,
      "d": 1,
      "l": 1,
      "cs": 80,
      "btts": 10
    },
    "法国": {
      "xG": 2.19,
      "xGA": 0.73,
      "ppg": 2.5,
      "gf": 26,
      "ga": 10,
      "p": 10,
      "w": 8,
      "d": 1,
      "l": 1,
      "cs": 20,
      "btts": 80
    },
    "科特迪瓦": {
      "xG": 1.56,
      "xGA": 1.01,
      "ppg": 2.5,
      "gf": 20,
      "ga": 7,
      "p": 10,
      "w": 8,
      "d": 1,
      "l": 1,
      "cs": 60,
      "btts": 40
    },
    "葡萄牙": {
      "xG": 2.34,
      "xGA": 0.91,
      "ppg": 2.3,
      "gf": 26,
      "ga": 9,
      "p": 10,
      "w": 7,
      "d": 2,
      "l": 1,
      "cs": 40,
      "btts": 50
    },
    "墨西哥": {
      "xG": 1.42,
      "xGA": 0.83,
      "ppg": 2.3,
      "gf": 18,
      "ga": 4,
      "p": 10,
      "w": 7,
      "d": 2,
      "l": 1,
      "cs": 70,
      "btts": 30
    },
    "西班牙": {
      "xG": 2.36,
      "xGA": 0.66,
      "ppg": 2.2,
      "gf": 25,
      "ga": 4,
      "p": 10,
      "w": 6,
      "d": 4,
      "l": 0,
      "cs": 70,
      "btts": 30
    },
    "比利时": {
      "xG": 2.35,
      "xGA": 0.86,
      "ppg": 2.2,
      "gf": 32,
      "ga": 7,
      "p": 10,
      "w": 6,
      "d": 4,
      "l": 0,
      "cs": 50,
      "btts": 50
    },
    "克罗地亚": {
      "xG": 2.02,
      "xGA": 1.0,
      "ppg": 2.2,
      "gf": 19,
      "ga": 10,
      "p": 10,
      "w": 7,
      "d": 1,
      "l": 2,
      "cs": 40,
      "btts": 50
    },
    "土耳其": {
      "xG": 1.81,
      "xGA": 1.24,
      "ppg": 2.2,
      "gf": 22,
      "ga": 13,
      "p": 10,
      "w": 7,
      "d": 1,
      "l": 2,
      "cs": 40,
      "btts": 40
    },
    "阿尔及利亚": {
      "xG": 1.28,
      "xGA": 1.13,
      "ppg": 2.2,
      "gf": 20,
      "ga": 6,
      "p": 10,
      "w": 7,
      "d": 1,
      "l": 2,
      "cs": 70,
      "btts": 10
    },
    "哥伦比亚": {
      "xG": 1.56,
      "xGA": 1.04,
      "ppg": 2.2,
      "gf": 25,
      "ga": 10,
      "p": 10,
      "w": 7,
      "d": 1,
      "l": 2,
      "cs": 50,
      "btts": 50
    },
    "塞内加尔": {
      "xG": 1.52,
      "xGA": 1.19,
      "ppg": 2.2,
      "gf": 17,
      "ga": 8,
      "p": 10,
      "w": 7,
      "d": 1,
      "l": 2,
      "cs": 60,
      "btts": 40
    },
    "挪威": {
      "xG": 1.8,
      "xGA": 1.04,
      "ppg": 2.1,
      "gf": 34,
      "ga": 9,
      "p": 10,
      "w": 6,
      "d": 3,
      "l": 1,
      "cs": 20,
      "btts": 80
    },
    "荷兰": {
      "xG": 1.68,
      "xGA": 0.92,
      "ppg": 2.1,
      "gf": 23,
      "ga": 9,
      "p": 10,
      "w": 6,
      "d": 3,
      "l": 1,
      "cs": 30,
      "btts": 60
    },
    "苏格兰": {
      "xG": 1.47,
      "xGA": 1.49,
      "ppg": 2.1,
      "gf": 22,
      "ga": 10,
      "p": 10,
      "w": 7,
      "d": 0,
      "l": 3,
      "cs": 30,
      "btts": 50
    },
    "日本": {
      "xG": 1.42,
      "xGA": 1.18,
      "ppg": 2.1,
      "gf": 15,
      "ga": 8,
      "p": 10,
      "w": 6,
      "d": 3,
      "l": 1,
      "cs": 60,
      "btts": 30
    },
    "刚果金": {
      "xG": 1.4,
      "xGA": 1.13,
      "ppg": 2.1,
      "gf": 12,
      "ga": 3,
      "p": 10,
      "w": 6,
      "d": 3,
      "l": 1,
      "cs": 70,
      "btts": 20
    },
    "韩国": {
      "xG": 1.3,
      "xGA": 1.03,
      "ppg": 1.9,
      "gf": 15,
      "ga": 13,
      "p": 10,
      "w": 6,
      "d": 1,
      "l": 3,
      "cs": 50,
      "btts": 20
    },
    "美国": {
      "xG": 1.52,
      "xGA": 1.12,
      "ppg": 1.9,
      "gf": 22,
      "ga": 16,
      "p": 10,
      "w": 6,
      "d": 1,
      "l": 3,
      "cs": 10,
      "btts": 80
    },
    "摩洛哥": {
      "xG": 1.54,
      "xGA": 0.94,
      "ppg": 1.9,
      "gf": 17,
      "ga": 5,
      "p": 10,
      "w": 5,
      "d": 4,
      "l": 1,
      "cs": 50,
      "btts": 0
    },
    "瑞士": {
      "xG": 1.58,
      "xGA": 1.0,
      "ppg": 1.7,
      "gf": 19,
      "ga": 9,
      "p": 10,
      "w": 4,
      "d": 5,
      "l": 1,
      "cs": 40,
      "btts": 60
    },
    "乌兹别克": {
      "xG": 1.2,
      "xGA": 1.35,
      "ppg": 1.7,
      "gf": 14,
      "ga": 7,
      "p": 10,
      "w": 5,
      "d": 2,
      "l": 3,
      "cs": 60,
      "btts": 30
    },
    "乌拉圭": {
      "xG": 1.38,
      "xGA": 1.07,
      "ppg": 1.7,
      "gf": 11,
      "ga": 8,
      "p": 10,
      "w": 4,
      "d": 5,
      "l": 1,
      "cs": 60,
      "btts": 40
    },
    "厄瓜多尔": {
      "xG": 1.38,
      "xGA": 0.99,
      "ppg": 1.7,
      "gf": 12,
      "ga": 6,
      "p": 10,
      "w": 4,
      "d": 5,
      "l": 1,
      "cs": 40,
      "btts": 50
    },
    "巴西": {
      "xG": 1.61,
      "xGA": 1.29,
      "ppg": 1.7,
      "gf": 23,
      "ga": 12,
      "p": 10,
      "w": 5,
      "d": 2,
      "l": 3,
      "cs": 20,
      "btts": 70
    },
    "佛得角": {
      "xG": 1.36,
      "xGA": 1.22,
      "ppg": 1.7,
      "gf": 17,
      "ga": 9,
      "p": 10,
      "w": 4,
      "d": 5,
      "l": 1,
      "cs": 60,
      "btts": 40
    },
    "捷克": {
      "xG": 1.42,
      "xGA": 1.1,
      "ppg": 1.6,
      "gf": 19,
      "ga": 11,
      "p": 10,
      "w": 4,
      "d": 4,
      "l": 2,
      "cs": 30,
      "btts": 0
    },
    "澳大利亚": {
      "xG": 0.91,
      "xGA": 1.49,
      "ppg": 1.6,
      "gf": 14,
      "ga": 10,
      "p": 10,
      "w": 5,
      "d": 1,
      "l": 4,
      "cs": 30,
      "btts": 40
    },
    "伊拉克": {
      "xG": 0.94,
      "xGA": 1.36,
      "ppg": 1.6,
      "gf": 11,
      "ga": 13,
      "p": 10,
      "w": 5,
      "d": 1,
      "l": 4,
      "cs": 20,
      "btts": 50
    },
    "埃及": {
      "xG": 0.98,
      "xGA": 1.46,
      "ppg": 1.6,
      "gf": 13,
      "ga": 7,
      "p": 10,
      "w": 4,
      "d": 4,
      "l": 2,
      "cs": 50,
      "btts": 40
    },
    "巴拿马": {
      "xG": 1.56,
      "xGA": 1.51,
      "ppg": 1.6,
      "gf": 18,
      "ga": 16,
      "p": 10,
      "w": 4,
      "d": 4,
      "l": 2,
      "cs": 10,
      "btts": 80
    },
    "伊朗": {
      "xG": 1.3,
      "xGA": 1.07,
      "ppg": 1.5,
      "gf": 16,
      "ga": 8,
      "p": 10,
      "w": 4,
      "d": 3,
      "l": 3,
      "cs": 50,
      "btts": 40
    },
    "加拿大": {
      "xG": 1.38,
      "xGA": 0.69,
      "ppg": 1.5,
      "gf": 9,
      "ga": 5,
      "p": 10,
      "w": 3,
      "d": 6,
      "l": 1,
      "cs": 60,
      "btts": 30
    },
    "约旦": {
      "xG": 1.34,
      "xGA": 1.44,
      "ppg": 1.4,
      "gf": 16,
      "ga": 17,
      "p": 10,
      "w": 4,
      "d": 2,
      "l": 4,
      "cs": 30,
      "btts": 60
    },
    "海地": {
      "xG": 1.25,
      "xGA": 1.47,
      "ppg": 1.4,
      "gf": 15,
      "ga": 11,
      "p": 10,
      "w": 4,
      "d": 2,
      "l": 4,
      "cs": 40,
      "btts": 30
    },
    "库拉索": {
      "xG": 1.25,
      "xGA": 1.75,
      "ppg": 1.4,
      "gf": 20,
      "ga": 21,
      "p": 10,
      "w": 4,
      "d": 2,
      "l": 4,
      "cs": 40,
      "btts": 0
    },
    "巴拉圭": {
      "xG": 1.22,
      "xGA": 1.15,
      "ppg": 1.4,
      "gf": 13,
      "ga": 13,
      "p": 10,
      "w": 4,
      "d": 2,
      "l": 4,
      "cs": 40,
      "btts": 50
    },
    "波黑": {
      "xG": 1.6,
      "xGA": 1.23,
      "ppg": 1.3,
      "gf": 15,
      "ga": 11,
      "p": 10,
      "w": 2,
      "d": 7,
      "l": 1,
      "cs": 10,
      "btts": 90
    },
    "南非": {
      "xG": 1.61,
      "xGA": 0.88,
      "ppg": 1.2,
      "gf": 12,
      "ga": 13,
      "p": 10,
      "w": 3,
      "d": 3,
      "l": 4,
      "cs": 10,
      "btts": 70
    },
    "突尼斯": {
      "xG": 1.12,
      "xGA": 1.46,
      "ppg": 1.2,
      "gf": 12,
      "ga": 17,
      "p": 10,
      "w": 3,
      "d": 3,
      "l": 4,
      "cs": 30,
      "btts": 50
    },
    "瑞典": {
      "xG": 1.26,
      "xGA": 1.57,
      "ppg": 1.1,
      "gf": 16,
      "ga": 19,
      "p": 10,
      "w": 3,
      "d": 2,
      "l": 5,
      "cs": 0,
      "btts": 0
    },
    "加纳": {
      "xG": 1.03,
      "xGA": 1.34,
      "ppg": 1.1,
      "gf": 11,
      "ga": 14,
      "p": 10,
      "w": 3,
      "d": 2,
      "l": 5,
      "cs": 30,
      "btts": 30
    },
    "沙特": {
      "xG": 0.93,
      "xGA": 1.51,
      "ppg": 0.9,
      "gf": 8,
      "ga": 12,
      "p": 10,
      "w": 2,
      "d": 3,
      "l": 5,
      "cs": 30,
      "btts": 40
    },
    "卡塔尔": {
      "xG": 1.11,
      "xGA": 1.45,
      "ppg": 0.7,
      "gf": 6,
      "ga": 14,
      "p": 10,
      "w": 1,
      "d": 4,
      "l": 5,
      "cs": 20,
      "btts": 0
    },
    "新西兰": {
      "xG": 1.19,
      "xGA": 1.84,
      "ppg": 0.5,
      "gf": 7,
      "ga": 19,
      "p": 10,
      "w": 1,
      "d": 2,
      "l": 7,
      "cs": 0,
      "btts": 50
    }
  },
  "h2h": {
    "卡塔尔_瑞士": {
      "team_a": "卡塔尔",
      "team_b": "瑞士",
      "total": 1,
      "wins_a": 0,
      "wins_b": 0,
      "draws": 1,
      "avg_goals": 2.0,
      "draw_rate": 1.0
    },
    "巴西_摩洛哥": {
      "team_a": "巴西",
      "team_b": "摩洛哥",
      "total": 1,
      "wins_a": 0,
      "wins_b": 0,
      "draws": 1,
      "avg_goals": 2.0,
      "draw_rate": 1.0
    },
    "海地_苏格兰": {
      "team_a": "海地",
      "team_b": "苏格兰",
      "total": 1,
      "wins_a": 0,
      "wins_b": 1,
      "draws": 0,
      "avg_goals": 1.0,
      "draw_rate": 0.0
    },
    "库拉索_德国": {
      "team_a": "库拉索",
      "team_b": "德国",
      "total": 1,
      "wins_a": 1,
      "wins_b": 0,
      "draws": 0,
      "avg_goals": 8.0,
      "draw_rate": 0.0
    },
    "日本_荷兰": {
      "team_a": "日本",
      "team_b": "荷兰",
      "total": 1,
      "wins_a": 0,
      "wins_b": 0,
      "draws": 1,
      "avg_goals": 4.0,
      "draw_rate": 1.0
    },
    "厄瓜多尔_科特迪瓦": {
      "team_a": "厄瓜多尔",
      "team_b": "科特迪瓦",
      "total": 1,
      "wins_a": 1,
      "wins_b": 0,
      "draws": 0,
      "avg_goals": 1.0,
      "draw_rate": 0.0
    },
    "瑞典_突尼斯": {
      "team_a": "瑞典",
      "team_b": "突尼斯",
      "total": 1,
      "wins_a": 1,
      "wins_b": 0,
      "draws": 0,
      "avg_goals": 6.0,
      "draw_rate": 0.0
    },
    "佛得角_西班牙": {
      "team_a": "佛得角",
      "team_b": "西班牙",
      "total": 1,
      "wins_a": 0,
      "wins_b": 0,
      "draws": 1,
      "avg_goals": 0.0,
      "draw_rate": 1.0
    },
    "埃及_比利时": {
      "team_a": "埃及",
      "team_b": "比利时",
      "total": 1,
      "wins_a": 0,
      "wins_b": 0,
      "draws": 1,
      "avg_goals": 2.0,
      "draw_rate": 1.0
    },
    "乌拉圭_沙特": {
      "team_a": "乌拉圭",
      "team_b": "沙特",
      "total": 1,
      "wins_a": 0,
      "wins_b": 0,
      "draws": 1,
      "avg_goals": 2.0,
      "draw_rate": 1.0
    },
    "伊朗_新西兰": {
      "team_a": "伊朗",
      "team_b": "新西兰",
      "total": 1,
      "wins_a": 0,
      "wins_b": 0,
      "draws": 1,
      "avg_goals": 4.0,
      "draw_rate": 1.0
    }
  },
  "tournament_stage": "knockout"
}